snowcatcher/__init__.py
snowcatcher/connect.py
snowcatcher/connect_and_query.py
snowcatcher/execute_query.py
snowcatcher/read_query.py
snowcatcher-2022.1.15.dist-info/LICENSE
snowcatcher-2022.1.15.dist-info/METADATA
snowcatcher-2022.1.15.dist-info/WHEEL
snowcatcher-2022.1.15.dist-info/top_level.txt
snowcatcher-2022.1.15.dist-info/RECORD
