Metadata-Version: 2.1
Name: snowcatcher
Version: 2022.1.15
Summary: Setup a snowflake connection and execute queries. Connection is setup via service account secrets or SSO web authintication login
Home-page: UNKNOWN
Author: Todd.Jordan
License: UNKNOWN
Platform: UNKNOWN
Requires-Dist: pandas
Requires-Dist: pyyaml
Requires-Dist: snowflake.connector-python
